arcane/secret.py
arcane_secret-0.3.0.dist-info/METADATA
arcane_secret-0.3.0.dist-info/WHEEL
arcane_secret-0.3.0.dist-info/RECORD
